AUTHORS
ChangeLog
LICENSE
README.rst
setup.cfg
setup.py
stacktask_tempest_plugin/README.rst
stacktask_tempest_plugin/__init__.py
stacktask_tempest_plugin/config.py
stacktask_tempest_plugin/plugin.py
stacktask_tempest_plugin/stacktask_client.py
stacktask_tempest_plugin.egg-info/PKG-INFO
stacktask_tempest_plugin.egg-info/SOURCES.txt
stacktask_tempest_plugin.egg-info/dependency_links.txt
stacktask_tempest_plugin.egg-info/entry_points.txt
stacktask_tempest_plugin.egg-info/not-zip-safe
stacktask_tempest_plugin.egg-info/pbr.json
stacktask_tempest_plugin.egg-info/top_level.txt
stacktask_tempest_plugin/services/__init__.py
stacktask_tempest_plugin/tests/__init__.py
stacktask_tempest_plugin/tests/base.py
stacktask_tempest_plugin/tests/api/__init__.py
stacktask_tempest_plugin/tests/api/test_users.py
stacktask_tempest_plugin/tests/scenario/__init__.py
stacktask_tempest_plugin/tests/scenario/test_invite_user.py
stacktask_tempest_plugin/tests/scenario/test_signup.py