Metadata-Version: 1.1
Name: stacktask-tempest-plugin
Version: 0.0.7
Summary: Tempest plugin for the Stacktask project
Home-page: https://github.com/catalyst/stacktask-tempest
Author: Dale Smith
Author-email: dale@catalyst-eu.net
License: UNKNOWN
Keywords: Plugin
Platform: UNKNOWN
Classifier: Development Status :: 4 - Beta
Classifier: Environment :: Console
Classifier: Environment :: OpenStack
Classifier: Intended Audience :: Information Technology
Classifier: Intended Audience :: System Administrators
Classifier: License :: OSI Approved :: Apache Software License
Classifier: Operating System :: POSIX :: Linux
Classifier: Natural Language :: English
Classifier: Topic :: Software Development :: Quality Assurance
Classifier: Topic :: Software Development :: Testing
Classifier: Programming Language :: Python
Classifier: Programming Language :: Python :: 2.7
